{"code":200,"msg":"操作成功","data":[{"percent":"5.56%","range":"[194542-194542]"},{"percent":"5.56%","range":"[214109-214109]"},{"percent":"5.56%","range":"[29852-29852]"},{"percent":"5.56%","range":"[47861-47861]"},{"percent":"5.56%","range":"[82244-82244]"},{"percent":"5.56%","range":"[95167-95167]"},{"percent":"5.56%","range":"[496470-496470]"},{"percent":"5.56%","range":"[680619-680619]"},{"percent":"5.56%","range":"[121837-121837]"},{"percent":"5.56%","range":"[20106-20106]"},{"percent":"5.56%","range":"[37688-37688]"},{"percent":"5.56%","range":"[250253-250253]"},{"percent":"5.56%","range":"[76179-76179]"},{"percent":"5.56%","range":"[90346-90346]"},{"percent":"5.56%","range":"[389351-389351]"},{"percent":"5.56%","range":"[559072-559072]"},{"percent":"5.56%","range":"[867069-867069]"},{"percent":"5.56%","range":"[165843-165843]"}]}
